bitchute/__init__.py
bitchute/bitchute.py
bitchute_scraper-0.1.8.dist-info/LICENSE
bitchute_scraper-0.1.8.dist-info/METADATA
bitchute_scraper-0.1.8.dist-info/WHEEL
bitchute_scraper-0.1.8.dist-info/top_level.txt
bitchute_scraper-0.1.8.dist-info/RECORD
