Metadata-Version: 2.1
Name: bitchute-scraper
Version: 0.1.8
Summary: A package to scrape BitChute platform recommendations using Selenium.
Home-page: https://github.com/bumatic/bitchute-scraper
Author: Marcus Burkhardt
Author-email: marcus.burkhardt@gmail.com
License: UNKNOWN
Platform: UNKNOWN
Classifier: Programming Language :: Python :: 3
Classifier: License :: OSI Approved :: MIT License
Classifier: Operating System :: OS Independent
Requires-Python: >=3.6
License-File: LICENSE
Requires-Dist: beautifulsoup4
Requires-Dist: markdownify
Requires-Dist: pandas
Requires-Dist: python-dateutil
Requires-Dist: retrying
Requires-Dist: selenium
Requires-Dist: tqdm
Requires-Dist: webdriver-manager
